unstract/connectors/__init__.py
unstract/connectors/base.py
unstract/connectors/connectorkit.py
unstract/connectors/constants.py
unstract/connectors/databases/__init__.py
unstract/connectors/databases/bigquery/__init__.py
unstract/connectors/databases/bigquery/bigquery.py
unstract/connectors/databases/bigquery/static/json_schema.json
unstract/connectors/databases/mariadb/__init__.py
unstract/connectors/databases/mariadb/mariadb.py
unstract/connectors/databases/mariadb/static/json_schema.json
unstract/connectors/databases/mssql/__init__.py
unstract/connectors/databases/mssql/mssql.py
unstract/connectors/databases/mssql/static/json_schema.json
unstract/connectors/databases/mysql/__init__.py
unstract/connectors/databases/mysql/mysql.py
unstract/connectors/databases/mysql/static/json_schema.json
unstract/connectors/databases/postgresql/__init__.py
unstract/connectors/databases/postgresql/postgresql.py
unstract/connectors/databases/postgresql/static/json_schema.json
unstract/connectors/databases/redshift/__init__.py
unstract/connectors/databases/redshift/redshift.py
unstract/connectors/databases/redshift/static/json_schema.json
unstract/connectors/databases/register.py
unstract/connectors/databases/snowflake/__init__.py
unstract/connectors/databases/snowflake/snowflake.py
unstract/connectors/databases/snowflake/static/json_schema.json
unstract/connectors/databases/unstract_db.py
unstract/connectors/enums.py
unstract/connectors/exceptions.py
unstract/connectors/filesystems/__init__.py
unstract/connectors/filesystems/api_storage/__init__.py
unstract/connectors/filesystems/api_storage/api_storage.py
unstract/connectors/filesystems/api_storage/static/json_schema.json
unstract/connectors/filesystems/box/__init__.py
unstract/connectors/filesystems/box/box.py
unstract/connectors/filesystems/box/static/json_schema.json
unstract/connectors/filesystems/google_drive/__init__.py
unstract/connectors/filesystems/google_drive/constants.py
unstract_connectors-0.0.3.dist-info/METADATA
unstract_connectors-0.0.3.dist-info/WHEEL
unstract_connectors-0.0.3.dist-info/RECORD
