Metadata-Version: 2.1
Name: unstract-connectors
Version: 0.0.3
Summary: All connectors that are part of the Unstract platform
Author-Email: Zipstack Inc. <devsupport@zipstack.com>
License: MIT
Classifier: Programming Language :: Python
Requires-Python: >=3.9
Requires-Dist: google-auth==2.20.0
Requires-Dist: google-cloud-secret-manager==2.16.1
Requires-Dist: google-cloud-storage==2.9.0
Requires-Dist: s3fs[boto3]==2023.6.0
Requires-Dist: PyDrive2[fsspec]==1.15.4
Requires-Dist: oauth2client==4.1.3
Requires-Dist: dropboxdrivefs==1.3.1
Requires-Dist: boxfs==0.2.1
Requires-Dist: psycopg2-binary==2.9.9
Requires-Dist: snowflake-connector-python[pandas]~=3.6.0
Requires-Dist: google-cloud-bigquery==3.11.4
Requires-Dist: pymssql==2.2.8
Requires-Dist: PyMySQL==1.1.0
